clyngor/__init__.py
clyngor/__main__.py
clyngor/answers.py
clyngor/as_pyasp.py
clyngor/decoder.py
clyngor/grounding.py
clyngor/inline.py
clyngor/parsing.py
clyngor/propagators.py
clyngor/solving.py
clyngor/upapi.py
clyngor/utils.py
clyngor/test/__init__.py
clyngor/test/conftest.py
clyngor/test/definitions.py
clyngor/test/test_answers.py
clyngor/test/test_api.py
clyngor/test/test_clingo_module.py
clyngor/test/test_decoder.py
clyngor/test/test_grounding.py
clyngor/test/test_parsing.py
clyngor/test/test_propagator_class.py
clyngor/test/test_solving.py
clyngor/test/test_stress.py
clyngor/test/test_time_limit.py
clyngor/test/test_upapi.py
clyngor/test/test_utils.py
clyngor-0.4.3.dist-info/LICENCE
clyngor-0.4.3.dist-info/METADATA
clyngor-0.4.3.dist-info/WHEEL
clyngor-0.4.3.dist-info/top_level.txt
clyngor-0.4.3.dist-info/RECORD
