Metadata-Version: 2.1
Name: clyngor
Version: 0.4.3
Summary: Python wrapper around Clingo/Answer Set Programming
Home-page: https://github.com/aluriak/clyngor
Author: Lucas Bourneuf
Author-email: lucas.bourneuf@laposte.net
License: GPLv3
Keywords: Answer Set Programming,wrapper,clingo
Platform: UNKNOWN
Classifier: License :: OSI Approved :: GNU General Public License v3 (GPLv3)
Classifier: Development Status :: 4 - Beta
Classifier: Intended Audience :: Science/Research
Classifier: Programming Language :: Python :: 3
Classifier: Programming Language :: Python :: 3.5
Classifier: Programming Language :: Python :: 3.6
Classifier: Programming Language :: Python :: 3.7
Classifier: Programming Language :: Python :: 3.8
Classifier: Programming Language :: Python :: 3.9
Classifier: Programming Language :: Python :: 3.10
Classifier: Programming Language :: ASP
License-File: LICENCE
Requires-Dist: Arpeggio (>=1.6.1)
Requires-Dist: pyPEG2 (>=2.15.2)
Requires-Dist: pytest (>=3.2.1)
Requires-Dist: clingo (>=5.5.1)
